LICENSE
MANIFEST.in
README.md
setup.py
cbpi4_MCP23017Actor/MCP23017_I2C.py
cbpi4_MCP23017Actor/__init__.py
cbpi4_MCP23017Actor/config.yaml
cbpi4_MCP23017Actor.egg-info/PKG-INFO
cbpi4_MCP23017Actor.egg-info/SOURCES.txt
cbpi4_MCP23017Actor.egg-info/dependency_links.txt
cbpi4_MCP23017Actor.egg-info/top_level.txt
cbpi4_MCP23017Actor/static/cbpi.png
cbpi4_MCP23017Actor/static/index.html
cbpi4_MCP23017Actor/static/style.css