Metadata-Version: 2.1
Name: cbpi4-MCP23017Actor
Version: 2.0.0
Summary: CraftBeerPi Plugin
Home-page: https://WagyHof.com
Author: Lawrence Wagy
Author-email: lnwagy@gmail.com
License-File: LICENSE
